Metadata-Version: 2.1
Name: dbbot-sqlalchemy-karate
Version: 0.5
Summary: A tool for inserting Robot Framework test run results into SQL database using SQLAlchemy.
Home-page: https://github.com/kumparan/DbBot-SQLAlchemy
Author: Robot Framework Developers, Pawel Bylicki
Author-email: robotframework@gmail.com
License: Apache License 2.0
Download-URL: https://pypi.python.org/pypi/dbbot-sqlalchemy-custom
Keywords: robotframework testing testautomation atdd
Platform: any
Classifier: Development Status :: 4 - Beta 
Classifier: License :: OSI Approved :: Apache Software License
Classifier: Operating System :: OS Independent
Classifier: Programming Language :: Python
Classifier: Topic :: Software Development :: Testing
License-File: LICENSE.txt
Requires-Dist: robotframework
Requires-Dist: sqlalchemy
